odoo/addons/purchase_order_line_receipt_status/README.rst
odoo/addons/purchase_order_line_receipt_status/__init__.py
odoo/addons/purchase_order_line_receipt_status/__manifest__.py
odoo/addons/purchase_order_line_receipt_status/i18n/es.po
odoo/addons/purchase_order_line_receipt_status/i18n/it.po
odoo/addons/purchase_order_line_receipt_status/i18n/purchase_order_line_receipt_status.pot
odoo/addons/purchase_order_line_receipt_status/models/__init__.py
odoo/addons/purchase_order_line_receipt_status/models/purchase_order_line.py
odoo/addons/purchase_order_line_receipt_status/readme/CONTRIBUTORS.rst
odoo/addons/purchase_order_line_receipt_status/readme/DESCRIPTION.rst
odoo/addons/purchase_order_line_receipt_status/readme/USAGE.rst
odoo/addons/purchase_order_line_receipt_status/static/description/icon.png
odoo/addons/purchase_order_line_receipt_status/static/description/index.html
odoo/addons/purchase_order_line_receipt_status/views/purchase_order_line.xml
odoo_addon_purchase_order_line_receipt_status-16.0.1.0.0.6.dist-info/METADATA
odoo_addon_purchase_order_line_receipt_status-16.0.1.0.0.6.dist-info/WHEEL
odoo_addon_purchase_order_line_receipt_status-16.0.1.0.0.6.dist-info/top_level.txt
odoo_addon_purchase_order_line_receipt_status-16.0.1.0.0.6.dist-info/RECORD
